whatshow_phy_mod_otfs/OTFS.py
whatshow_phy_mod_otfs/OTFSDetector.py
whatshow_phy_mod_otfs/OTFSResGrid.py
whatshow_phy_mod_otfs/__init__.py
whatshow_phy_mod_otfs-2.1.17.dist-info/METADATA
whatshow_phy_mod_otfs-2.1.17.dist-info/WHEEL
whatshow_phy_mod_otfs-2.1.17.dist-info/top_level.txt
whatshow_phy_mod_otfs-2.1.17.dist-info/RECORD
