Metadata-Version: 2.2
Name: whatshow_phy_mod_otfs
Version: 2.1.17
Dynamic: description
Dynamic: description-content-type
